dock_py_selenium/dock/dock.py
dock_py_selenium-2.1.4.dist-info/METADATA
dock_py_selenium-2.1.4.dist-info/WHEEL
dock_py_selenium-2.1.4.dist-info/top_level.txt
dock_py_selenium-2.1.4.dist-info/RECORD
