Metadata-Version: 2.1
Name: dock-py-selenium
Version: 2.1.4
Summary: A startup / mockup folder for a selenium project with custom methods.
Home-page: https://github.com/iambstha/dock-py-selenium
Author: Bishal Shrestha
Author-email: iambstha@gmail.com
License: MIT
Keywords: selenium,automation,testing
Classifier: Development Status :: 2 - Pre-Alpha
Classifier: Intended Audience :: Developers
Classifier: License :: OSI Approved :: MIT License
Classifier: Programming Language :: Python :: 3.9
Requires-Dist: selenium
